README.md
setup.py
novaposhta/__init__.py
novaposhta/api.py
novaposhta/conf.py
novaposhta/exceptions.py
novaposhta/models.py
novaposhta/serializer.py
novaposhta/tests.py
novaposhta_api_client.egg-info/PKG-INFO
novaposhta_api_client.egg-info/SOURCES.txt
novaposhta_api_client.egg-info/dependency_links.txt
novaposhta_api_client.egg-info/requires.txt
novaposhta_api_client.egg-info/top_level.txt
novaposhta_api_client.egg-info/zip-safe